symbolite/__init__.py
symbolite/py.typed
symbolite/abstract/__init__.py
symbolite/abstract/scalar.py
symbolite/abstract/symbol.py
symbolite/abstract/vector.py
symbolite/core/__init__.py
symbolite/core/symbolgroup.py
symbolite/core/util.py
symbolite/impl/__init__.py
symbolite/impl/libjax/__init__.py
symbolite/impl/libjax/scalar.py
symbolite/impl/libjax/symbol.py
symbolite/impl/libjax/vector.py
symbolite/impl/libnumpy/__init__.py
symbolite/impl/libnumpy/scalar.py
symbolite/impl/libnumpy/symbol.py
symbolite/impl/libnumpy/vector.py
symbolite/impl/libstd/__init__.py
symbolite/impl/libstd/scalar.py
symbolite/impl/libstd/symbol.py
symbolite/impl/libstd/vector.py
symbolite/impl/libsympy/__init__.py
symbolite/impl/libsympy/scalar.py
symbolite/impl/libsympy/symbol.py
symbolite/impl/libsympy/vector.py
symbolite/testsuite/test_depen.py
symbolite/testsuite/test_operator_precedence.py
symbolite/testsuite/test_scalar_function.py
symbolite/testsuite/test_scalar_impls.py
symbolite/testsuite/test_scalar_str.py
symbolite/testsuite/test_serialize.py
symbolite/testsuite/test_symbol.py
symbolite/testsuite/test_symbolgroup.py
symbolite/testsuite/test_vector.py
symbolite-0.6.0.dist-info/AUTHORS
symbolite-0.6.0.dist-info/LICENSE
symbolite-0.6.0.dist-info/METADATA
symbolite-0.6.0.dist-info/WHEEL
symbolite-0.6.0.dist-info/top_level.txt
symbolite-0.6.0.dist-info/RECORD
