Metadata-Version: 2.1
Name: symbolite
Version: 0.6.0
Summary: A minimalistic symbolic package.
Author-email: "Hernán E. Grecco" <hernan.grecco@gmail.com>, Mauro Silberberg <maurosilber@gmail.com>
License: MIT License
Project-URL: Homepage, https://github.com/hgrecco/symbolite
Project-URL: Bug Tracker, https://github.com/hgrecco/symbolite/issues
Keywords: symbolic
Classifier: Programming Language :: Python :: 3.10
Classifier: Programming Language :: Python :: 3.11
Classifier: Programming Language :: Python :: 3.12
Classifier: License :: OSI Approved :: MIT License
Classifier: Operating System :: OS Independent
Classifier: Intended Audience :: Developers
Classifier: Intended Audience :: Science/Research
Classifier: Topic :: Scientific/Engineering
Classifier: Topic :: Software Development :: Libraries
Requires-Python: >=3.10
License-File: LICENSE
License-File: AUTHORS
Requires-Dist: typing-extensions
Provides-Extra: test
Requires-Dist: pytest ; extra == 'test'
Requires-Dist: pytest-mypy-testing ; extra == 'test'
